jupyter_json_viewer/__init__.py
jupyter_json_viewer/viewer.py
jupyter_json_viewer/tests/__init__.py
jupyter_json_viewer/tests/test_viewer.py
jupyter_json_viewer-0.1.5.dist-info/METADATA
jupyter_json_viewer-0.1.5.dist-info/WHEEL
jupyter_json_viewer-0.1.5.dist-info/top_level.txt
jupyter_json_viewer-0.1.5.dist-info/RECORD
