Metadata-Version: 2.1
Name: jupyter-json-viewer
Version: 0.1.5
Summary: An interactive JSON viewer for Jupyter Notebooks
Author: Johannes Kaindl
License: GNU General Public License v3.0
Classifier: Programming Language :: Python :: 3
Classifier: License :: OSI Approved :: GNU General Public License v3 (GPLv3)
Classifier: Operating System :: OS Independent
Requires-Dist: IPython>=7.0.0
